bus_project_NJ/__init__.py
bus_project_NJ/src/__init__.py
bus_project_NJ/src/analyze.py
bus_project_NJ/src/collect_data.py
bus_project_NJ/src/data_processing_punctuality.py
bus_project_NJ/src/data_processing_speed.py
bus_project_NJ/src/data_processing_theaters.py
bus_project_NJ/src/fetch_bus_routes.py
bus_project_NJ/src/fetch_bus_schedules.py
bus_project_NJ/src/fetch_bus_stops.py
bus_project_NJ/src/fetch_current_positions.py
bus_project_NJ/src/fetch_theaters.py
bus_project_NJ/src/filter_data.py
bus_project_NJ/src/filter_data_punctuality.py
bus_project_NJ/src/helper_functions.py
test/__init__.py
test/test_data_analysis.py
test/test_fetch_data.py
test/test_filter_data.py
bus_project_NJ-0.0.3.dist-info/LICENSE
bus_project_NJ-0.0.3.dist-info/METADATA
bus_project_NJ-0.0.3.dist-info/WHEEL
bus_project_NJ-0.0.3.dist-info/top_level.txt
bus_project_NJ-0.0.3.dist-info/RECORD
