Metadata-Version: 2.1
Name: bus_project_NJ
Version: 0.0.3
Summary: A package for analysing public transport data
Home-page: https://gitlab.mimuw.edu.pl/nj448267/python_project_nj
Author: Natalia J.
Author-email: njunkiert@gmail.com
Classifier: Programming Language :: Python :: 3
Classifier: License :: OSI Approved :: MIT License
Classifier: Operating System :: OS Independent
Requires-Python: >=3.6
License-File: LICENSE
